pydropbox/__init__.py
pydropbox/pydropbox.py
pydropbox-0.1.0.dist-info/METADATA
pydropbox-0.1.0.dist-info/RECORD
pydropbox-0.1.0.dist-info/WHEEL
pydropbox-0.1.0.dist-info/top_level.txt
